lightning/__init__.py
lightning/__main__.py
lightning/backend.py
lightning/interfaces.py
lightning/server.py
lightning/structs.py
lightning/utility.py
lightning_server-0.7.4.dist-info/LICENSE
lightning_server-0.7.4.dist-info/METADATA
lightning_server-0.7.4.dist-info/WHEEL
lightning_server-0.7.4.dist-info/top_level.txt
lightning_server-0.7.4.dist-info/RECORD
