Metadata-Version: 2.1
Name: lightning-server
Version: 0.7.4
Summary: A socket-based light server framework
Author-email: la <1784574357@qq.com>
License: MIT License
Project-URL: Homepage, https://github.com/labo-China/lightning
Project-URL: Bug Tracker, https://github.com/labo-China/lightning/issues
Project-URL: Source Code, https://github.com/labo-China/lightning
Classifier: Programming Language :: Python :: 3
Classifier: License :: OSI Approved :: MIT License
Classifier: Operating System :: OS Independent
Classifier: Topic :: Internet :: WWW/HTTP :: HTTP Servers
Classifier: Development Status :: 4 - Beta
Classifier: Intended Audience :: Developers
Requires-Python: >=3.6
License-File: LICENSE
